{
    "index.html": [
        {
            "operation": "TYPED",
            "lines": 0,
            "keyStrokeTimeStamp": "Wed Jul 21 2021 10:49:38",
            "keyStrokeInfo": " ",
            "position": "49,57"
        },
        {
            "operation": "PASTE",
            "lines": 1,
            "keyStrokeTimeStamp": "Wed Jul 21 2021 10:49:39",
            "keyStrokeInfo": "cursor: url(target.svg) 15 15, move;",
            "position": "49,58"
        },
        {
            "operation": "DELETE",
            "lines": 0,
            "keyStrokeTimeStamp": "Wed Jul 21 2021 10:49:45",
            "keyStrokeInfo": "",
            "position": "49,70"
        },
        {
            "operation": "TYPED",
            "lines": 0,
            "keyStrokeTimeStamp": "Wed Jul 21 2021 10:49:46",
            "keyStrokeInfo": "''",
            "position": "49,70"
        },
        {
            "operation": "PASTE",
            "lines": 1,
            "keyStrokeTimeStamp": "Wed Jul 21 2021 10:50:11",
            "keyStrokeInfo": "images\\stick1.gif",
            "position": "49,71"
        },
        {
            "operation": "DELETE",
            "lines": 0,
            "keyStrokeTimeStamp": "Wed Jul 21 2021 10:50:13",
            "keyStrokeInfo": "",
            "position": "49,77"
        },
        {
            "operation": "TYPED",
            "lines": 0,
            "keyStrokeTimeStamp": "Wed Jul 21 2021 10:50:13",
            "keyStrokeInfo": "/",
            "position": "49,77"
        },
        {
            "operation": "DELETE",
            "lines": 0,
            "keyStrokeTimeStamp": "Wed Jul 21 2021 10:50:48",
            "keyStrokeInfo": "",
            "position": "49,86"
        },
        {
            "operation": "DELETE",
            "lines": 0,
            "keyStrokeTimeStamp": "Wed Jul 21 2021 10:50:48",
            "keyStrokeInfo": "",
            "position": "49,86"
        },
        {
            "operation": "DELETE",
            "lines": 0,
            "keyStrokeTimeStamp": "Wed Jul 21 2021 10:50:49",
            "keyStrokeInfo": "",
            "position": "49,85"
        },
        {
            "operation": "TYPED",
            "lines": 0,
            "keyStrokeTimeStamp": "Wed Jul 21 2021 10:50:49",
            "keyStrokeInfo": "p",
            "position": "49,85"
        },
        {
            "operation": "TYPED",
            "lines": 0,
            "keyStrokeTimeStamp": "Wed Jul 21 2021 10:50:50",
            "keyStrokeInfo": "n",
            "position": "49,86"
        },
        {
            "operation": "TYPED",
            "lines": 0,
            "keyStrokeTimeStamp": "Wed Jul 21 2021 10:50:50",
            "keyStrokeInfo": "g",
            "position": "49,87"
        },
        {
            "operation": "TYPED",
            "lines": 0,
            "keyStrokeTimeStamp": "Wed Jul 21 2021 10:51:04",
            "keyStrokeInfo": "a",
            "position": "49,98"
        },
        {
            "operation": "TYPED",
            "lines": 0,
            "keyStrokeTimeStamp": "Wed Jul 21 2021 10:51:04",
            "keyStrokeInfo": "u",
            "position": "49,99"
        },
        {
            "operation": "TYPED",
            "lines": 0,
            "keyStrokeTimeStamp": "Wed Jul 21 2021 10:51:04",
            "keyStrokeInfo": "t",
            "position": "49,100"
        },
        {
            "operation": "TYPED",
            "lines": 0,
            "keyStrokeTimeStamp": "Wed Jul 21 2021 10:51:04",
            "keyStrokeInfo": "o",
            "position": "49,101"
        },
        {
            "operation": "DELETE",
            "lines": 0,
            "keyStrokeTimeStamp": "Wed Jul 21 2021 10:55:07",
            "keyStrokeInfo": "",
            "position": "49,72"
        },
        {
            "operation": "DELETE",
            "lines": 0,
            "keyStrokeTimeStamp": "Wed Jul 21 2021 10:55:08",
            "keyStrokeInfo": "",
            "position": "49,71"
        },
        {
            "operation": "DELETE",
            "lines": 0,
            "keyStrokeTimeStamp": "Wed Jul 21 2021 10:55:11",
            "keyStrokeInfo": "",
            "position": "49,79"
        },
        {
            "operation": "DELETE",
            "lines": 0,
            "keyStrokeTimeStamp": "Wed Jul 21 2021 10:55:11",
            "keyStrokeInfo": "",
            "position": "49,78"
        },
        {
            "operation": "TYPED",
            "lines": 0,
            "keyStrokeTimeStamp": "Wed Jul 21 2021 10:55:12",
            "keyStrokeInfo": "j",
            "position": "49,78"
        },
        {
            "operation": "TYPED",
            "lines": 0,
            "keyStrokeTimeStamp": "Wed Jul 21 2021 10:55:13",
            "keyStrokeInfo": "p",
            "position": "49,79"
        },
        {
            "operation": "TYPED",
            "lines": 0,
            "keyStrokeTimeStamp": "Wed Jul 21 2021 10:55:14",
            "keyStrokeInfo": "e",
            "position": "49,80"
        },
        {
            "operation": "DELETE",
            "lines": 0,
            "keyStrokeTimeStamp": "Wed Jul 21 2021 10:55:27",
            "keyStrokeInfo": "",
            "position": "49,85"
        },
        {
            "operation": "TYPED",
            "lines": 0,
            "keyStrokeTimeStamp": "Wed Jul 21 2021 10:59:43",
            "keyStrokeInfo": "g",
            "position": "49,78"
        },
        {
            "operation": "TYPED",
            "lines": 0,
            "keyStrokeTimeStamp": "Wed Jul 21 2021 10:59:44",
            "keyStrokeInfo": "i",
            "position": "49,79"
        },
        {
            "operation": "TYPED",
            "lines": 0,
            "keyStrokeTimeStamp": "Wed Jul 21 2021 10:59:45",
            "keyStrokeInfo": "f",
            "position": "49,80"
        },
        {
            "operation": "TYPED",
            "lines": 0,
            "keyStrokeTimeStamp": "Wed Jul 21 2021 10:59:53",
            "keyStrokeInfo": "/",
            "position": "49,71"
        },
        {
            "operation": "TYPED",
            "lines": 0,
            "keyStrokeTimeStamp": "Wed Jul 21 2021 10:59:54",
            "keyStrokeInfo": "i",
            "position": "49,71"
        },
        {
            "operation": "TYPED",
            "lines": 0,
            "keyStrokeTimeStamp": "Wed Jul 21 2021 10:59:54",
            "keyStrokeInfo": "m",
            "position": "49,72"
        },
        {
            "operation": "TYPED",
            "lines": 0,
            "keyStrokeTimeStamp": "Wed Jul 21 2021 10:59:54",
            "keyStrokeInfo": "a",
            "position": "49,73"
        },
        {
            "operation": "TYPED",
            "lines": 0,
            "keyStrokeTimeStamp": "Wed Jul 21 2021 10:59:55",
            "keyStrokeInfo": "g",
            "position": "49,74"
        },
        {
            "operation": "TYPED",
            "lines": 0,
            "keyStrokeTimeStamp": "Wed Jul 21 2021 10:59:55",
            "keyStrokeInfo": "e",
            "position": "49,75"
        },
        {
            "operation": "TYPED",
            "lines": 0,
            "keyStrokeTimeStamp": "Wed Jul 21 2021 10:59:55",
            "keyStrokeInfo": "s",
            "position": "49,76"
        },
        {
            "operation": "TYPED",
            "lines": 0,
            "keyStrokeTimeStamp": "Wed Jul 21 2021 11:02:18",
            "keyStrokeInfo": "c",
            "position": "49,71"
        },
        {
            "operation": "TYPED",
            "lines": 0,
            "keyStrokeTimeStamp": "Wed Jul 21 2021 11:02:18",
            "keyStrokeInfo": "u",
            "position": "49,72"
        },
        {
            "operation": "TYPED",
            "lines": 0,
            "keyStrokeTimeStamp": "Wed Jul 21 2021 11:02:19",
            "keyStrokeInfo": "r",
            "position": "49,73"
        },
        {
            "operation": "TYPED",
            "lines": 0,
            "keyStrokeTimeStamp": "Wed Jul 21 2021 11:02:19",
            "keyStrokeInfo": "s",
            "position": "49,74"
        },
        {
            "operation": "TYPED",
            "lines": 0,
            "keyStrokeTimeStamp": "Wed Jul 21 2021 11:02:19",
            "keyStrokeInfo": "o",
            "position": "49,75"
        },
        {
            "operation": "TYPED",
            "lines": 0,
            "keyStrokeTimeStamp": "Wed Jul 21 2021 11:02:20",
            "keyStrokeInfo": "r",
            "position": "49,76"
        },
        {
            "operation": "TYPED",
            "lines": 0,
            "keyStrokeTimeStamp": "Wed Jul 21 2021 11:02:21",
            "keyStrokeInfo": ".",
            "position": "49,77"
        },
        {
            "operation": "TYPED",
            "lines": 0,
            "keyStrokeTimeStamp": "Wed Jul 21 2021 11:02:21",
            "keyStrokeInfo": "c",
            "position": "49,78"
        },
        {
            "operation": "TYPED",
            "lines": 0,
            "keyStrokeTimeStamp": "Wed Jul 21 2021 11:02:21",
            "keyStrokeInfo": "u",
            "position": "49,79"
        },
        {
            "operation": "TYPED",
            "lines": 0,
            "keyStrokeTimeStamp": "Wed Jul 21 2021 11:02:22",
            "keyStrokeInfo": "r",
            "position": "49,80"
        },
        {
            "operation": "DELETE",
            "lines": 0,
            "keyStrokeTimeStamp": "Wed Jul 21 2021 11:02:38",
            "keyStrokeInfo": "",
            "position": "49,58"
        },
        {
            "operation": "PASTE",
            "lines": 1,
            "keyStrokeTimeStamp": "Wed Jul 21 2021 11:02:41",
            "keyStrokeInfo": "cursor: url('cursor.cur') , auto;",
            "position": "37,1"
        }
    ]
}